dwave_micro_client.py
dwave_micro_client-0.2.2.dist-info/DESCRIPTION.rst
dwave_micro_client-0.2.2.dist-info/METADATA
dwave_micro_client-0.2.2.dist-info/RECORD
dwave_micro_client-0.2.2.dist-info/WHEEL
dwave_micro_client-0.2.2.dist-info/metadata.json
dwave_micro_client-0.2.2.dist-info/top_level.txt
