Metadata-Version: 1.0
Name: dwave-micro-client
Version: 0.2.2
Summary: A minimal client for interacting with SAPI servers.
Home-page: https://github.com/dwavesystems/dwave_micro_client
Author: UNKNOWN
Author-email: UNKNOWN
License: UNKNOWN
Platform: UNKNOWN
